foolbox/VERSION
foolbox/__init__.py
foolbox/criteria.py
foolbox/devutils.py
foolbox/distances.py
foolbox/gradient_estimators.py
foolbox/plot.py
foolbox/py.typed
foolbox/tensorboard.py
foolbox/types.py
foolbox/utils.py
foolbox/attacks/__init__.py
foolbox/attacks/additive_noise.py
foolbox/attacks/base.py
foolbox/attacks/basic_iterative_method.py
foolbox/attacks/binarization.py
foolbox/attacks/blended_noise.py
foolbox/attacks/blur.py
foolbox/attacks/boundary_attack.py
foolbox/attacks/brendel_bethge.py
foolbox/attacks/carlini_wagner.py
foolbox/attacks/contrast.py
foolbox/attacks/contrast_min.py
foolbox/attacks/dataset_attack.py
foolbox/attacks/ddn.py
foolbox/attacks/deepfool.py
foolbox/attacks/ead.py
foolbox/attacks/fast_gradient_method.py
foolbox/attacks/fast_minimum_norm.py
foolbox/attacks/gen_attack.py
foolbox/attacks/gen_attack_utils.py
foolbox/attacks/gradient_descent_base.py
foolbox/attacks/hop_skip_jump.py
foolbox/attacks/inversion.py
foolbox/attacks/mi_fgsm.py
foolbox/attacks/newtonfool.py
foolbox/attacks/pointwise.py
foolbox/attacks/projected_gradient_descent.py
foolbox/attacks/saltandpepper.py
foolbox/attacks/sparse_l1_descent_attack.py
foolbox/attacks/spatial_attack.py
foolbox/attacks/spatial_attack_transformations.py
foolbox/attacks/virtual_adversarial_attack.py
foolbox/data/cifar100_00_49.png
foolbox/data/cifar100_01_33.png
foolbox/data/cifar100_02_72.png
foolbox/data/cifar100_03_51.png
foolbox/data/cifar100_04_71.png
foolbox/data/cifar100_05_92.png
foolbox/data/cifar100_06_15.png
foolbox/data/cifar100_07_14.png
foolbox/data/cifar100_08_23.png
foolbox/data/cifar100_09_0.png
foolbox/data/cifar100_10_71.png
foolbox/data/cifar100_11_75.png
foolbox/data/cifar100_12_81.png
foolbox/data/cifar100_13_69.png
foolbox/data/cifar100_14_40.png
foolbox/data/cifar100_15_43.png
foolbox/data/cifar100_16_92.png
foolbox/data/cifar100_17_97.png
foolbox/data/cifar100_18_70.png
foolbox/data/cifar100_19_53.png
foolbox/data/cifar10_00_3.png
foolbox/data/cifar10_01_8.png
foolbox-3.3.4.dist-info/LICENSE
foolbox-3.3.4.dist-info/METADATA
foolbox-3.3.4.dist-info/WHEEL
foolbox-3.3.4.dist-info/top_level.txt
foolbox-3.3.4.dist-info/RECORD
