Metadata-Version: 2.1
Name: foolbox
Version: 3.3.4
Summary: Foolbox is an adversarial attacks library that works natively with PyTorch, TensorFlow and JAX
Home-page: https://github.com/bethgelab/foolbox
Author: Jonas Rauber, Roland S. Zimmermann
Author-email: foolbox+rzrolandzimmermann@gmail.com
License: MIT License
Platform: UNKNOWN
Classifier: Development Status :: 3 - Alpha
Classifier: Intended Audience :: Developers
Classifier: Intended Audience :: Science/Research
Classifier: License :: OSI Approved :: MIT License
Classifier: Programming Language :: Python :: 3
Classifier: Programming Language :: Python :: 3.6
Classifier: Programming Language :: Python :: 3.7
Classifier: Topic :: Scientific/Engineering :: Artificial Intelligence
License-File: LICENSE
Requires-Dist: numpy
Requires-Dist: scipy
Requires-Dist: setuptools
Requires-Dist: eagerpy >=0.30.0
Requires-Dist: GitPython >=3.0.7
Requires-Dist: typing-extensions >=3.7.4.1
Requires-Dist: requests >=2.24.0
Provides-Extra: testing
Requires-Dist: pytest >=7.1.1 ; extra == 'testing'
Requires-Dist: pytest-cov >=3.0.0 ; extra == 'testing'
